picopyn/__init__.py
picopyn/client.py
picopyn/connection.py
picopyn/pool.py
picopyn-0.1.1.dist-info/AUTHORS.md
picopyn-0.1.1.dist-info/LICENSE
picopyn-0.1.1.dist-info/METADATA
picopyn-0.1.1.dist-info/WHEEL
picopyn-0.1.1.dist-info/top_level.txt
picopyn-0.1.1.dist-info/RECORD
