Metadata-Version: 2.1
Name: picopyn
Version: 0.1.1
Summary: Async connector for working with the distributed Picodata database.
Author-email: Asya Lomakina <a.lomakina@picodata.io>, Igor Kuznetsov <i.kuznetsov@picodata.io>, Dmitriy Кoltsov <dkoltsov@picodata.io>
License: BSD-2-Clause
Project-URL: Homepage, https://git.picodata.io/solution/picopyn
Keywords: database,picodata
Classifier: Programming Language :: Python :: 3.9
Classifier: License :: OSI Approved :: BSD License
Classifier: Operating System :: OS Independent
Classifier: Development Status :: 3 - Alpha
Classifier: Intended Audience :: Developers
Classifier: Topic :: Database
Classifier: Framework :: AsyncIO
Requires-Python: ==3.9
License-File: LICENSE
License-File: AUTHORS.md
Requires-Dist: async-timeout ==5.0.1
Requires-Dist: asyncpg ==0.30.0
Requires-Dist: typing-extensions ==4.12.2 ; python_version == "3.9"
Provides-Extra: docs
Requires-Dist: pdoc ==15.0.4 ; extra == 'docs'
Requires-Dist: pyright ==1.1.396 ; extra == 'docs'
Provides-Extra: gssauth
Requires-Dist: gssapi ; (platform_system != "Windows") and extra == 'gssauth'
Requires-Dist: sspilib ; (platform_system == "Windows") and extra == 'gssauth'
Provides-Extra: test
Requires-Dist: pytest ==8.3.5 ; extra == 'test'
Requires-Dist: pytest-asyncio ==0.25.3 ; extra == 'test'
Requires-Dist: ruff ==0.11.13 ; extra == 'test'
Requires-Dist: mypy ==1.16.0 ; extra == 'test'
Requires-Dist: black ==25.1.0 ; extra == 'test'
